LICENSE
README.md
django_toyo_auth/__init__.py
django_toyo_auth/admin.py
django_toyo_auth/apps.py
django_toyo_auth/models.py
django_toyo_auth/providers/__init__.py
django_toyo_auth/providers/iniad/__init__.py
django_toyo_auth/providers/iniad/provider.py
django_toyo_auth/providers/iniad/tests.py
django_toyo_auth/providers/iniad/urls.py
django_toyo_auth/providers/iniad/views.py
django_toyo_auth/providers/toyo/__init__.py
django_toyo_auth/providers/toyo/provider.py
django_toyo_auth/providers/toyo/tests.py
django_toyo_auth/providers/toyo/urls.py
django_toyo_auth/providers/toyo/views.py
django_toyo_auth/signals.py
django_toyo_auth/tests.py
django_toyo_auth/views.py
django_toyo_auth-0.9.0.dist-info/METADATA
django_toyo_auth-0.9.0.dist-info/WHEEL
django_toyo_auth-0.9.0.dist-info/LICENSE
django_toyo_auth-0.9.0.dist-info/RECORD
