Metadata-Version: 2.1
Name: django-toyo-auth
Version: 0.9.0
Summary: It offers providers of Toyo University and INIAD Accounts for django-allauth
Home-page: http://github.com/ayame-q/django-toyo-auth
License: MIT
Keywords: django-allauth,django,INIAD,Toyo Univ,東洋大学
Author: ayame.space
Author-email: ayame.space@gmail.com
Requires-Python: >=3.6,<4.0
Classifier: Framework :: Django
Classifier: Framework :: Django :: 3.0
Classifier: Framework :: Django :: 3.1
Classifier: Framework :: Django :: 3.2
Classifier: Framework :: Django :: 4.0
Classifier: Framework :: Django :: 4.1
Classifier: License :: OSI Approved :: MIT License
Classifier: Programming Language :: Python
Classifier: Programming Language :: Python :: 3
Classifier: Programming Language :: Python :: 3.6
Classifier: Programming Language :: Python :: 3.7
Classifier: Programming Language :: Python :: 3.8
Classifier: Programming Language :: Python :: 3.9
Classifier: Programming Language :: Python :: 3.10
Classifier: Programming Language :: Python :: 3.11
Classifier: Programming Language :: Python :: 3
Classifier: Programming Language :: Python :: 3.10
Classifier: Programming Language :: Python :: 3.11
Classifier: Programming Language :: Python :: 3.6
Classifier: Programming Language :: Python :: 3.7
Classifier: Programming Language :: Python :: 3.8
Classifier: Programming Language :: Python :: 3.9
Classifier: Topic :: Education
Classifier: Topic :: System :: Systems Administration :: Authentication/Directory
Requires-Dist: Django
Requires-Dist: django-allauth
Project-URL: Documentation, https://github.com/ayame-q/django-toyo-auth#readme
Project-URL: Repository, http://github.com/ayame-q/django-toyo-auth
